{"/5TxP6rB5Xsj6wML99MSww==":"logo2.png","m3xv8yGrGWZ4O/bEz3LB+Q==":"women-1.jpg","6Wxb3s6ocFYEtkfVh/cZaQ==":"word-1.jpg","HfO7NJnweXRDZvw8YXVz8A==":"word-3.jpg","6m/OU/XBUwrRH0ZXfTq4Ow==":"word-2.jpg","kn7qXpK11Bx/xxf45/U0pA==":"word-4.jpg","IQZLhYtqcuQgJrqLH44HeA==":"word-5.jpg","vSH+D/f1uynalms0oTVrlA==":"word-6.jpg","Cj73YKUSweiqZWIyBQIMyA==":"man-3.jpg","3mFfXUT1y8B3fwSyXYr0aQ==":"office-3.jpg","jnww8yLvDWoYnNgDwkA8tA==":"sneakers.jpg","rF1qRX1X2N1JiZWeaOxUmA==":"porsche.jpg","KMgIMb2VOgnkgkZZalrrJQ==":"bike.jpg","DW3izTzZPnAwHlq6YXV1iQ==":"team1.jpg","FdhK5xex5lG+IFoSKix1zA==":"team2.jpg","qb71uR5rI2P+sE0WiHyXNg==":"interion.jpg","b+buQZikE+5p3sfc8xp+eg==":"team3.jpg","AFWbLwGHsp27Mh8eDJZRQQ==":"people-3.jpg","IS6ZMXNrwkOUuDfC+fLF3Q==":"people-1.jpg","fGtEck5sgPRBIhyCb256Uw==":"people-5.jpg","2MPMaoYZ8jRAHgut82ScUA==":"people-6.jpg","cmJ7PpOCTEr6dSMzCZ+wDA==":"people-4.jpg","Cu2DpAN8j8FAVP+lY8cxGQ==":"people-2.jpg","BYkFurULi1/d9Pm0xGeZkw==":"team4.jpg","2s3Psk66VH0LhdN8qmgm1Q==":"namaar.comlogo-96x24.png","JaEjqTRUXG+EVKDfoYXSuQ==":"namaar.comlogo-486x120.png","EE8mbpjYZoHDCJUoGgueJg==":"mbr-1920x1280.jpg","NauJZMHd7oNruD395eXR6w==":"namaar.com-full-2000x1413.png","BryNk5xwBkVJQU6jxulTOA==":"mbr-1920x1279.jpg","ByLbHAhFagt9gQvd8LsRpw==":"namaar.com-full-1-2000x1413.png","78EE9eclQcaJwxMslEQhkw==":"mbr-965x643.jpg","cy2O6CenP+fpN6+FOPTvbQ==":"namaar.comlogo.png","TQKKYluEg3q4GPyE4wc0Kg==":"namaar.comlogo.svg","Zwp7s1KfLzR8eITFuzhu6w==":"namaar.comlogo-1.svg","Iqe22Dz4fJk5bi34dFh1Cg==":"logo.svg","xbE7zvKKCP/B8kyzrg0CsQ==":"mbr-1480x987.jpg","ZyjfuAAXmmTIIrwAU0jIhQ==":"logo_picture-1500x1500.png","ab/oWcXcWA6EvwUxCKFQDA==":"logo_picture-2000x1399.png","9Z0Jh0u4BZ78Ks1AqH269g==":"mbr-1920x1284.jpg","qxtDSjwYvDx4AXvTYXnK/w==":"mbr-1920x1227.jpg","XRJIsyNpAj+hubCWAKlGVA==":"logo-1.svg","biQDknKPPNsH7c8ggozyyw==":"logo_picture-1-2000x1399.png","54VI3jH7GSxvdAWWgcy8Dw==":"mbr-1920x1280.jpeg","4CXycLjh1decaWfGKyqY4Q==":"4space-office-3-1100x744.jpg","TwDNq1Vt+DdGWRHJCUX9Uw==":"4space-office-3-1100x744.jpeg","xBdcGNPZDHhoZVPmeAUnTg==":"i2c-5-940x564.jpeg","ID05R93w9Ai1XrrmKsN6oQ==":"8db2545f-7fe1-43a6-ba74-fee73fecaf97-1200x900.jpeg","PW1a16+GjcTxwTpuV3zBAA==":"bf7f1be1-c792-4ebd-955d-ef6262999833-1200x1600.jpeg","FLCryvWSq22/4iWSs+csAg==":"3c3728cb-09f8-4c1c-8cf4-842095cab52c-780x439.jpeg","p2r/4Lyl4q15MJqro19a9A==":"a98bf2e2-78a4-4879-a0f6-a9173bd77649-780x439.jpg","2AE9OAPknCY9Xmh4ifaeKw==":"f065d5ab-a876-45ad-8a50-f32f1acd97c6-780x439.jpg","Dz1Th9bzMIPPduiEOAkCfA==":"man-4.jpg","5AXzOFUwsKjQN97g/GlzAw==":"thumbnail_img-3096-780x1040.jpeg","jrlraF/hslNRCVAYPEIG8A==":"db6ce319-1364-4b6f-b2aa-eb2468ec9356-780x1040.jpeg","Qed0UmFxsCDzTi1TYN9v5Q==":"img-3268-1125x2436.png","rciqnlj/KXxj7rgtng5zdg==":"features4.jpg","mQSxBpPL69cdSYxMPXiyQw==":"img-2985-780x1040.jpeg","v4Jh7zNTZ2Qi31R9Do9Qng==":"img-1664-780x1040.jpeg","wTQKHFvIo9RPlVOV7E0vbA==":"img-1895%20(1)-780x1040.jpeg","kgIxivoDJmTC3i9izN0t7g==":"img-1913-780x1040.jpeg","9WyuVDYdy0WYQtWYnxQfgg==":"img-1865-780x1040.jpeg","0QeCEQi2xbi4l7ieaSCReg==":"512px-ministry_of_foriegn_affairs_logo.svg-254x248.png","Tk3sd7D3J/RVPCisH5+HNA==":"1200px-%D8%A7%D9%84%D8%AF%D9%81%D8%A7%D8%B9_%D8%A7%D9%84%D9%85%D8%AF%D9%86%D9%8A_%D8%A7%D9%84%D8%B3%D8%B9%D9%88%D8%AF%D9%8A.svg-254x229.png","9IOPY1xKVO1a53f85eXssA==":"20170618211409!%D8%B4%D8%B9%D8%A7%D8%B1_%D8%A7%D9%84%D9%85%D9%88%D9%94%D8%B3%D8%B3%D8%A9_%D8%A7%D9%84%D8%B9%D8%A7%D9%85%D8%A9_%D9%84%D9%84%D8%AE%D8%B7%D9%88%D8%B7_%D8%A7%D9%84%D8%AD%D8%AF%D9%8A%D8%AF%D9%8A%D8%A9-254x254.jpg","k6pTSFltDGucfHEdEW0ubQ==":"ca875758d118-254x150.jpg","VKB2DaFDaPp9P+vgAvJD2g==":"%D8%A7%D9%84%D9%87%D9%8A%D9%8A%D9%94%D8%A9-%D8%A7%D9%84%D8%B9%D8%A7%D9%85%D8%A9-%D9%84%D9%84%D8%BA%D8%B0%D8%A7%D8%A1-%D9%88%D8%A7%D9%84%D8%AF%D9%88%D8%A7%D8%A1-200x200.png","ugfF7yp+z+X9O4/qjZLnqw==":"%D8%B4%D8%B9%D8%A7%D8%B1_%D9%87%D9%8A%D9%8A%D9%94%D8%A9_%D8%AA%D9%82%D9%88%D9%8A%D9%85_%D8%A7%D9%84%D8%AA%D8%B9%D9%84%D9%8A%D9%85_%D9%88%D8%A7%D9%84%D8%AA%D8%AF%D8%B1%D9%8A%D8%A8_(%D8%A7%D9%84%D8%B3%D8%B9%D9%88%D8%AF%D9%8A%D8%A9)-254x98.png","TFTxEMtAU+SCvXGTzp5uFw==":"461px-ministry_of_islamic_affairs_in_saudi_arabia_logo.svg-254x332.png","P46QgC2hkrHPFkt9ytSi9g==":"18094-250x329.jpg","jsalV/cnxwmmCc0VmcCJ5Q==":"%D8%B4%D8%B9%D8%A7%D8%B1_%D9%82%D9%88%D8%A7%D8%AA_%D8%A7%D9%94%D9%85%D9%86_%D8%A7%D9%84%D9%85%D9%86%D8%B4%D8%A7%D9%93%D8%AA_%D8%A7%D9%84%D8%B3%D8%B9%D9%88%D8%AF%D9%8A%D8%A9_(2020)-254x254.png","oBC6l4Bo6fHFetP0k91FvA==":"1042516-98819066_6-3-254x156.png","+13XT8sCl7d4fvQVOj0KtA==":"461px-ministry_of_islamic_affairs_in_saudi_arabia_logo.svg-461x602.png","5B7gumiJLXjg4kRNoeNK9Q==":"%D8%B4%D8%B9%D8%A7%D8%B1_%D9%82%D9%88%D8%A7%D8%AA_%D8%A7%D9%94%D9%85%D9%86_%D8%A7%D9%84%D9%85%D9%86%D8%B4%D8%A7%D9%93%D8%AA_%D8%A7%D9%84%D8%B3%D8%B9%D9%88%D8%AF%D9%8A%D8%A9_(2020)-255x255.png","ZB0cYFclQ9Wjlu2lgo1rxA==":"img-2123-780x1040.jpeg","IXd2jA9qbmMLYzhqmprHAg==":"img-4480-780x1040.jpeg","TN+2pIRnBraQyY9EWtU4kA==":"background7.jpg","7JANaHDMxxCauVWm+q0sGA==":"img-5429-780x1179.jpeg","5Eh/zHdPqk+PQsVDmpLF3A==":"unnamed-780x1040.jpeg","MEu7ZW6tCuLJeTybTnxibA==":"img-3488-780x585.jpeg","pxlsRhbBHgS28hnmKZBJoQ==":"0964be5b-bed6-4769-8c7a-d0e390a9d815-780x490.jpeg","raVzVbGA6Q6eim4j8N7aUA==":"50977c2b-83c9-491a-9145-a5758ea6849a-780x461.jpeg","BZwppcDciWvOU/xM2Imhzw==":"26f2dc8f-0c16-46d6-8e08-d5ce6784fab6-780x585.jpeg","ni7RmmSNNFdaTLxxFvwCzw==":"3a78cd5a-3bae-4176-ae66-ca9605732af1-780x1040.jpeg","WEzphEIrCBJ7fBzYFXlkEQ==":"93605281-613f-48e8-a856-fb0bd8ff9359-766x612.jpeg","DufQxfnoa5EyNs0muD/O/A==":"a25fc2d3-ab2d-4e50-afbc-9db498b57560-780x1040.jpeg","Iwv5MTB8eVNdRVUHJ4OTPQ==":"8db2545f-7fe1-43a6-ba74-fee73fecaf97-780x585.jpeg","81yXDkhzceLU8oh4DkcNWA==":"bf7f1be1-c792-4ebd-955d-ef6262999833-780x1040.jpeg","7643PAPYqnD4y/yTBxTYuQ==":"d61ac150-075a-44c9-874e-125ebbbea0be-780x1040.jpeg","tLLJpRCGuO1/5eSujf3sxw==":"jyurfhvb_400x400-400x400.jpg","iN/bd/OW0y1f3IfhcT3rPQ==":"darah_logo.svg-459x547.png","FtzMoYmYBBleoc5qDJSqEw==":"461px-ministry_of_islamic_affairs_in_saudi_arabia_logo.svg-1-461x602.png","4gGgYXHkUEZJx0o3z1KMUg==":"nahilriyadh-white.svg","IR50eEAa/gjv9e3Jv2cWTg==":"background1.jpg","YOnoyrJclOz1Fg1L2lTfDg==":"riyadh%20design-1617x1078.png","mcpd2phIJpzHgErOVMNK+Q==":"mbr-1920x960.jpg","6xR6ehYFzJHc+yhR8NUv3A==":"untitled%20design-1920x1080.png","td+TuAm6gzMVJIYDfOd7PQ==":"background1-1.jpg","pn5wOcJaJq9Zsuh5QB0Uug==":"whatsapp%20image%202022-05-09%20at%205.58.12%20pm-379x379.jpg","NR8vWZbDO+l2pGEae9UnIg==":"whatsapp%20image%202022-05-09%20at%206.02.09%20pm-720x960.jpg","xERByCHp+dibnuGqZf9ncA==":"whatsapp%20image%202022-05-09%20at%206.02.09%20pm-720x960.jpeg","qJWUDPpfj/rmnBDnP+CJXA==":"whatsapp%20image%202022-05-09%20at%205.02.49%20pm-720x1017.jpeg"}